AUTHORS.rst
CONTRIBUTING.rst
HISTORY.rst
LICENSE
MANIFEST.in
README.rst
setup.cfg
setup.py
activation/__init__.py
activation/activation.py
activation/cli.py
activation.egg-info/PKG-INFO
activation.egg-info/SOURCES.txt
activation.egg-info/dependency_links.txt
activation.egg-info/entry_points.txt
activation.egg-info/not-zip-safe
activation.egg-info/requires.txt
activation.egg-info/top_level.txt
docs/Makefile
docs/activation.rst
docs/authors.rst
docs/conf.py
docs/contributing.rst
docs/history.rst
docs/index.rst
docs/installation.rst
docs/make.bat
docs/modules.rst
docs/readme.rst
docs/usage.rst
docs/_build/html/_static/ajax-loader.gif
docs/_build/html/_static/comment-bright.png
docs/_build/html/_static/comment-close.png
docs/_build/html/_static/comment.png
docs/_build/html/_static/down-pressed.png
docs/_build/html/_static/down.png
docs/_build/html/_static/file.png
docs/_build/html/_static/minus.png
docs/_build/html/_static/plus.png
docs/_build/html/_static/up-pressed.png
docs/_build/html/_static/up.png
tests/__init__.py
tests/test_activation.py