Metadata-Version: 1.1
Name: activation
Version: 0.1.0
Summary: activation function for machine learning
Home-page: https://github.com/deybvagm/activation
Author: Deyber Arley Valencia Gomez
Author-email: valencia.arley4@gmail.com
License: MIT license
Keywords: activation
Platform: UNKNOWN
Classifier: Development Status :: 2 - Pre-Alpha
Classifier: Intended Audience :: Developers
Classifier: License :: OSI Approved :: MIT License
Classifier: Natural Language :: English
Classifier: Programming Language :: Python :: 2
Classifier: Programming Language :: Python :: 2.7
Classifier: Programming Language :: Python :: 3
Classifier: Programming Language :: Python :: 3.4
Classifier: Programming Language :: Python :: 3.5
Classifier: Programming Language :: Python :: 3.6
